recommendx/__init__.py
recommendx/reccode.py
recommendx/timecode.py
recommendx-0.1.dist-info/LICENSE
recommendx-0.1.dist-info/METADATA
recommendx-0.1.dist-info/WHEEL
recommendx-0.1.dist-info/top_level.txt
recommendx-0.1.dist-info/RECORD
